wikitext_asymptote/__init__.py
wikitext_asymptote/parse.py
wikitext_asymptote-0.0.4.dist-info/LICENSE
wikitext_asymptote-0.0.4.dist-info/METADATA
wikitext_asymptote-0.0.4.dist-info/WHEEL
wikitext_asymptote-0.0.4.dist-info/top_level.txt
wikitext_asymptote-0.0.4.dist-info/RECORD
