Metadata-Version: 2.1
Name: wikitext-asymptote
Version: 0.0.4
Summary: Custom wikitext parser to produce html, plain text fields and relevant links from wikipedia page source code.
Author-email: Aitor Pérez <aitor.perez@epfl.ch>, Ramtin Yazdanian <ramtin.yazdanian@epfl.ch>
Project-URL: Homepage, https://github.com/epflgraph/wikitext-asymptote
Project-URL: Bug Tracker, https://github.com/epflgraph/wikitext-asymptote/issues
Classifier: Programming Language :: Python :: 3
Classifier: License :: OSI Approved :: MIT License
Classifier: Operating System :: OS Independent
Requires-Python: >=3.7
License-File: LICENSE
Requires-Dist: mwparserfromhell
